e2eAIOK/__init__.py
e2eAIOK/version
e2eAIOK/ModelAdapter/__init__.py
e2eAIOK/ModelAdapter/default_ma.conf
e2eAIOK/ModelAdapter/main.py
e2eAIOK/ModelAdapter/backbone/__init__.py
e2eAIOK/ModelAdapter/backbone/factory.py
e2eAIOK/ModelAdapter/backbone/unet/__init__.py
e2eAIOK/ModelAdapter/backbone/unet/generic_UNet.py
e2eAIOK/ModelAdapter/backbone/unet/generic_UNet_DA.py
e2eAIOK/ModelAdapter/dataset/__init__.py
e2eAIOK/ModelAdapter/dataset/cifar.py
e2eAIOK/ModelAdapter/dataset/composed_dataset.py
e2eAIOK/ModelAdapter/dataset/office31.py
e2eAIOK/ModelAdapter/engine_core/__init__.py
e2eAIOK/ModelAdapter/engine_core/transferrable_model.py
e2eAIOK/ModelAdapter/engine_core/adapter/__init__.py
e2eAIOK/ModelAdapter/engine_core/adapter/factory.py
e2eAIOK/ModelAdapter/engine_core/adapter/adversarial/DA_Loss.py
e2eAIOK/ModelAdapter/engine_core/adapter/adversarial/__init__.py
e2eAIOK/ModelAdapter/engine_core/adapter/adversarial/adversarial_adapter.py
e2eAIOK/ModelAdapter/engine_core/adapter/adversarial/cdan_adapter.py
e2eAIOK/ModelAdapter/engine_core/adapter/adversarial/dann_adapter.py
e2eAIOK/ModelAdapter/engine_core/adapter/adversarial/discriminator.py
e2eAIOK/ModelAdapter/engine_core/adapter/adversarial/grl.py
e2eAIOK/ModelAdapter/engine_core/adapter/traditional/__init__.py
e2eAIOK/ModelAdapter/engine_core/distiller/__init__.py
e2eAIOK/ModelAdapter/engine_core/distiller/basic_distiller.py
e2eAIOK/ModelAdapter/engine_core/distiller/dkd.py
e2eAIOK/ModelAdapter/engine_core/distiller/kd.py
e2eAIOK/ModelAdapter/engine_core/distiller/utils/__init__.py
e2eAIOK/ModelAdapter/engine_core/distiller/utils/aug_random.py
e2eAIOK/ModelAdapter/engine_core/distiller/utils/dataset_wrapper.py
e2eAIOK/ModelAdapter/engine_core/distiller/utils/deal_logits.py
e2eAIOK/ModelAdapter/engine_core/distiller/utils/manager.py
e2eAIOK/ModelAdapter/engine_core/finetunner/__init__.py
e2eAIOK/ModelAdapter/engine_core/finetunner/basic_finetunner.py
e2eAIOK/ModelAdapter/training/__init__.py
e2eAIOK_ModelAdapter-1.0.0.dist-info/LICENSE
e2eAIOK_ModelAdapter-1.0.0.dist-info/METADATA
e2eAIOK_ModelAdapter-1.0.0.dist-info/WHEEL
e2eAIOK_ModelAdapter-1.0.0.dist-info/top_level.txt
e2eAIOK_ModelAdapter-1.0.0.dist-info/RECORD
